doter/commands/__init__.py
doter/commands/clean.py
doter/commands/install.py
doter/config/__init__.py
doter/exceptions.py
doter/ui/__init__.py
doter/ui/cleanup_ui.py
doter/ui/install_ui.py
doter/utils.py
doter-1.0.2.dist-info/LICENSE
doter-1.0.2.dist-info/METADATA
doter-1.0.2.dist-info/WHEEL
doter-1.0.2.dist-info/entry_points.txt
doter-1.0.2.dist-info/RECORD
